pfcm_ekm/EKM.py
pfcm_ekm/PFCM.py
pfcm_ekm/__init__.py
pfcm_ekm-0.1.0.dist-info/licenses/LICENSE
pfcm_ekm-0.1.0.dist-info/METADATA
pfcm_ekm-0.1.0.dist-info/WHEEL
pfcm_ekm-0.1.0.dist-info/top_level.txt
pfcm_ekm-0.1.0.dist-info/RECORD
