Metadata-Version: 2.4
Name: pfcm-ekm
Version: 0.1.0
Summary: PFCM (Possibilistic Fuzzy C-Means) and EKM (Equilibrium K-Means) in one clustering package
Author-email: Fajar <muhfajarags@gmail.com>
License: MIT
Project-URL: Homepage, https://github.com/muhfajarags/Sumber-Kode-PFCM-dan-EKM
Project-URL: Repository, https://github.com/muhfajarags/Sumber-Kode-PFCM-dan-EKM
Project-URL: Issues, https://github.com/muhfajarags/Sumber-Kode-PFCM-dan-EKM/issues
Keywords: clustering,kmeans,fuzzy,pfcm,ekm,imbalanced
Classifier: Programming Language :: Python :: 3
Classifier: License :: OSI Approved :: MIT License
Classifier: Intended Audience :: Science/Research
Classifier: Topic :: Scientific/Engineering :: Artificial Intelligence
Classifier: Topic :: Scientific/Engineering :: Information Analysis
Requires-Python: >=3.9
License-File: LICENSE
Requires-Dist: numpy>=1.21
Requires-Dist: scikit-learn>=1.1
Provides-Extra: accel
Requires-Dist: numba>=0.57; extra == "accel"
Dynamic: license-file
